cloudman/__init__.py
cloudman/_version.py
cloudman/cli.py
cloudman/gcp/__init__.py
cloudman/gcp/boot.py
cloudman/gcp/constants.py
cloudman/gcp/disk.py
cloudman/gcp/firewall.py
cloudman/gcp/instance.py
cloudman/gcp/machine.py
cloudman/gcp/network.py
cloudman/gcp/project.py
cloudman/gcp/utils.py
cloudman/utils/__init__.py
cloudman/utils/logger.py
cloudman/utils/misc.py
cloudman-0.0.10.dist-info/METADATA
cloudman-0.0.10.dist-info/RECORD
cloudman-0.0.10.dist-info/WHEEL
cloudman-0.0.10.dist-info/entry_points.txt
cloudman-0.0.10.dist-info/top_level.txt
