Metadata-Version: 2.1
Name: cloudman
Version: 0.0.10
Summary: Command line tool for managing single-purpose cloud VMs
Home-page: https://github.com/aakashns/cloudman
Author: SwiftAce Inc.
Author-email: opensource@swiftace.ai
License: UNKNOWN
Platform: UNKNOWN
Classifier: Programming Language :: Python :: 3
Classifier: License :: OSI Approved :: MIT License
Classifier: Operating System :: OS Independent
Requires-Dist: fire
Requires-Dist: termcolor
